radiowinds/__init__.py
radiowinds/make_animation.py
radiowinds/radio_emission.py
radiowinds/test.py
radiowinds-0.0.2.dist-info/LICENSE.md
radiowinds-0.0.2.dist-info/METADATA
radiowinds-0.0.2.dist-info/WHEEL
radiowinds-0.0.2.dist-info/top_level.txt
radiowinds-0.0.2.dist-info/RECORD
