Metadata-Version: 2.1
Name: radiowinds
Version: 0.0.2
Summary: A package to calculate the thermal free-free emission from stellar winds
Home-page: https://github.com/Dualta93/radiowinds
Author: Dualta O Fionnagain
Author-email: ofionnad@tcd.ie
License: UNKNOWN
Platform: UNKNOWN
Classifier: Programming Language :: Python :: 3
Classifier: License :: OSI Approved :: MIT License
Classifier: Operating System :: OS Independent
